radontestprint.py
setup.py
radontestprint.egg-info/PKG-INFO
radontestprint.egg-info/SOURCES.txt
radontestprint.egg-info/dependency_links.txt
radontestprint.egg-info/top_level.txt