Metadata-Version: 1.0
Name: radontestprint
Version: 2.0
Summary: test pypi function
Home-page: UNKNOWN
Author: radonma
Author-email: rnmar@163.com
License: UNKNOWN
Platform: UNKNOWN
